cythonized_ta/cython_ta_funcs.cpython-312-darwin.so
cythonized_ta-0.0.0.dist-info/METADATA
cythonized_ta-0.0.0.dist-info/WHEEL
cythonized_ta-0.0.0.dist-info/top_level.txt
cythonized_ta-0.0.0.dist-info/RECORD
