Metadata-Version: 2.1
Name: cythonized-ta
Version: 0.0.0
Requires-Dist: Cython
Requires-Dist: numpy
